pytest_group_by_class/__init__.py
pytest_group_by_class-0.1.5.dist-info/METADATA
pytest_group_by_class-0.1.5.dist-info/WHEEL
pytest_group_by_class-0.1.5.dist-info/entry_points.txt
pytest_group_by_class-0.1.5.dist-info/top_level.txt
pytest_group_by_class-0.1.5.dist-info/RECORD
