Metadata-Version: 2.1
Name: pytest-group-by-class
Version: 0.1.5
Summary: A Pytest plugin for running a subset of your tests by splitting them in to groups of classes.
Home-page: https://github.com/marco-mn/pytest-group-by-class
Author: marco-mn
Author-email: snoopy@peanuts.com
Classifier: Development Status :: 5 - Production/Stable
Classifier: Intended Audience :: Developers
Classifier: License :: OSI Approved :: MIT License
Classifier: Operating System :: OS Independent
Classifier: Programming Language :: Python
Classifier: Topic :: Software Development :: Testing
Classifier: Programming Language :: Python :: 2.7
Classifier: Programming Language :: Python :: 3.7
Classifier: Programming Language :: Python :: 3.8
Requires-Dist: pytest (>=2.5)
